{
  "product": [
    {
      "ID": 1,
      "name_ar": "??????? ??????",
      "Name": "Nescafe classic",
      "code": 7891000000000,
      "Category_id": 6,
      "subcategory_id": 211,
      "unit_of_counting_Id": "",
      "weight_type_id": "",
      "pieces_per_box": "",
      "price": 750,
      "lengtth": "",
      "height": "",
      "description": "double cream,full flavor",
      "server_image_path": "nescafe_classic.jpg"
    },
    {
      "ID": 2,
      "name_ar": "??? ??????",
      "Name": "Gloria Hot Sauce",
      "code": 6281100000000,
      "Category_id": 4,
      "subcategory_id": 24,
      "unit_of_counting_Id": "",
      "weight_type_id": "",
      "pieces_per_box": "",
      "price": 420,
      "lengtth": "",
      "height": "",
      "description": "Hot&Fermented",
      "server_image_path": "Gloria_hot_sauce.jpg"
    },
    {
      "ID": 3,
      "name_ar": "?????",
      "Name": "Belage furniture polish",
      "code": 6282310000000,
      "Category_id": 12,
      "subcategory_id": 343,
      "unit_of_counting_Id": "",
      "weight_type_id": "",
      "pieces_per_box": "",
      "price": 700,
      "lengtth": "",
      "height": "",
      "description": "Furniture polish ???? ?????? ? ???? ?????????? ??????",
      "server_image_path": "Belage_furniture_polish.jpg"
    }
  ]
}